imghelp/__init__.py
imghelp/colorconv.py
imghelp/crop.py
imghelp/imgcompress.py
imghelp/imgrotate.py
imghelp-1.0.10.dist-info/LICENSE
imghelp-1.0.10.dist-info/WHEEL
imghelp-1.0.10.dist-info/METADATA
imghelp-1.0.10.dist-info/RECORD
