Metadata-Version: 2.1
Name: imghelp
Version: 1.0.10
Summary: Python package which contains 4 basic image processing functions.
License: MIT
Author: Sufang Tan, Jasmine Ortega, Ho Kwan Lio, Maeve Shi
Requires-Python: >=3.9,<4.0
Classifier: License :: OSI Approved :: MIT License
Classifier: Programming Language :: Python :: 3
Classifier: Programming Language :: Python :: 3.10
Classifier: Programming Language :: Python :: 3.9
Requires-Dist: matplotlib (>=3.4.3,<4.0.0)
Requires-Dist: numpy (>=1.21.0,<2.0.0)
